_iatransfer_setup/__init__.py
_iatransfer_setup/utils.py
iatransfer/toolkit/__init__.py
iatransfer/toolkit/base_matching.py
iatransfer/toolkit/base_score.py
iatransfer/toolkit/base_standardization.py
iatransfer/toolkit/base_transfer.py
iatransfer/toolkit/iat.py
iatransfer/toolkit/tli.py
iatransfer/toolkit/tli_helpers.py
iatransfer/toolkit/matching/__init__.py
iatransfer/toolkit/matching/bipartite_matching.py
iatransfer/toolkit/matching/dp_flat_matching.py
iatransfer/toolkit/matching/dp_matching.py
iatransfer/toolkit/matching/graph_matching.py
iatransfer/toolkit/matching/nbipartite_matching.py
iatransfer/toolkit/matching/random_matching.py
iatransfer/toolkit/score/__init__.py
iatransfer/toolkit/score/autoencoder_score.py
iatransfer/toolkit/score/shape_score.py
iatransfer/toolkit/standardization/__init__.py
iatransfer/toolkit/standardization/blocks_standardization.py
iatransfer/toolkit/standardization/flatten_standardization.py
iatransfer/toolkit/standardization/graph_standardization.py
iatransfer/toolkit/transfer/__init__.py
iatransfer/toolkit/transfer/clip_transfer.py
iatransfer/toolkit/transfer/full_transfer.py
iatransfer/toolkit/transfer/magnitude_transfer.py
iatransfer/toolkit/transfer/trace_transfer.py
iatransfer/toolkit/transfer/transfer_stats.py
iatransfer/utils/__init__.py
iatransfer/utils/dot_dict.py
iatransfer/utils/file_utils.py
iatransfer/utils/flatten.py
iatransfer/utils/subclass_utils.py
iatransfer-1.0.3.data/data/requirements.txt
iatransfer-1.0.3.data/data/setup_configuration.json
iatransfer-1.0.3.dist-info/LICENSE
iatransfer-1.0.3.dist-info/METADATA
iatransfer-1.0.3.dist-info/WHEEL
iatransfer-1.0.3.dist-info/top_level.txt
iatransfer-1.0.3.dist-info/RECORD
