Metadata-Version: 2.1
Name: iatransfer
Version: 1.0.3
Summary: Tool for inter-architecture weight transfer
Home-page: https://github.com/KamilPiechowiak/weights-transfer
Author: Kamil Piechowiak, Daniel Nowak, Maciej Czyżewski
Author-email: 
License: Apache-2.0
Keywords: transfer,learning,transfer learning,training,neural network,interarchitecture
Platform: UNKNOWN
Classifier: Programming Language :: Python :: 3
Classifier: Operating System :: POSIX :: Linux
Requires-Dist: nose (>=1.3.7)
Requires-Dist: numpy (>=1.19.4)
Requires-Dist: torch (>=1.6.0)
Requires-Dist: typing-extensions (>=3.7.4.3)
Requires-Dist: timm (>=0.3.3)
Requires-Dist: networkx (>=2.5)
Requires-Dist: graphviz (>=0.16)
Requires-Dist: efficientnet-pytorch (>=0.7)
Requires-Dist: inflection (>=0.5.1)
Requires-Dist: matplotlib (>=3.3.3)
Requires-Dist: karateclub (>=1.0.22)
